[{"Team":860,"Number":1,"Created":"2023-01-23T21:40:26.631092-05:00","Scouter":"David","Schema":"Charged Up Attempt 1","Color":"Red","Environment":"","Data":"[\"Docked\",\"Yes\",\"-1,-1,-1,-1,-1,-1,-1,-1,-1*-1,2,-1,2,-1,2,-1,-1,2*-1,2,-1,2,-1,-1,-1,2,-1\",\"0.68\",\"-1,-1,-1,-1,-1,-1,-1,-1,-1*-1,2,-1,2,-1,2,-1,-1,2*-1,2,-1,2,-1,-1,-1,2,-1\",\"Engaged\"]","Status":0,"Identifier":"3fa220a6-6153-4165-9971-3e0163745e5c","DeviceID":"04LBPEM2"},{"Team":861,"Number":2,"Created":"2023-01-23T21:40:57.530016-05:00","Scouter":"David","Schema":"Charged Up Attempt 1","Color":"Red","Environment":"","Data":"[\"\",\"No\",\"-1,-1,4,-1,-1,-1,-1,4,2*2,-1,2,-1,4,2,-1,-1,-1*-1,-1,-1,2,-1,-1,-1,2,-1\",\"2.97\",\"-1,-1,4,-1,-1,-1,-1,4,2*2,-1,2,-1,4,2,-1,-1,-1*-1,-1,-1,2,-1,-1,-1,2,-1\",\"Neither\"]","Status":0,"Identifier":"512d9ab0-c625-4f58-866c-965c77d311a3","DeviceID":"04LBPEM2"},{"Team":456,"Number":123,"Created":"2023-01-25T16:08:46.584248-05:00","Scouter":"A Person","Schema":"Charged Up Attempt 1","Color":"Red","Environment":"","Data":"[\"Docked\",\"Yes\",\"-1,-1,4,-1,-1,4,4,-1,-1*-1,2,-1,-1,2,-1,2,-1,-1*-1,2,-1,-1,-1,-1,-1,-1,-1\",\"16.47\",\"-1,-1,4,-1,-1,4,4,-1,-1*-1,2,-1,-1,2,-1,2,-1,-1*-1,2,-1,-1,-1,-1,-1,-1,-1\",\"\"]","Status":0,"Identifier":"c2f32414-3276-4a72-bb97-37568d060126","DeviceID":"04LBPEM2"}]
